pygobbler/__init__.py
pygobbler/_utils.py
pygobbler/allocate_upload_directory.py
pygobbler/approve_probation.py
pygobbler/clone_version.py
pygobbler/create_project.py
pygobbler/fetch_directory.py
pygobbler/fetch_file.py
pygobbler/fetch_latest.py
pygobbler/fetch_manifest.py
pygobbler/fetch_permissions.py
pygobbler/fetch_summary.py
pygobbler/fetch_usage.py
pygobbler/list_assets.py
pygobbler/list_files.py
pygobbler/list_projects.py
pygobbler/list_versions.py
pygobbler/refresh_latest.py
pygobbler/refresh_usage.py
pygobbler/reindex_version.py
pygobbler/reject_probation.py
pygobbler/remove_asset.py
pygobbler/remove_project.py
pygobbler/remove_version.py
pygobbler/reroute_links.py
pygobbler/service_info.py
pygobbler/set_permissions.py
pygobbler/start_gobbler.py
pygobbler/unpack_path.py
pygobbler/upload_directory.py
pygobbler/validate_version.py
pygobbler/version_path.py
pygobbler-0.1.11.dist-info/licenses/LICENSE.txt
pygobbler-0.1.11.dist-info/METADATA
pygobbler-0.1.11.dist-info/WHEEL
pygobbler-0.1.11.dist-info/top_level.txt
pygobbler-0.1.11.dist-info/RECORD
